dingtalk_utils/__init__.py
dingtalk_utils/client/__init__.py
dingtalk_utils/client/corp.py
dingtalk_utils/client/setting.py
dingtalk_utils/client/user.py
dingtalk_utils/contacts/__init__.py
dingtalk_utils/contacts/api.py
dingtalk_utils/department/__init__.py
dingtalk_utils/department/api.py
dingtalk_utils-1.0.4.dist-info/LICENSE
dingtalk_utils-1.0.4.dist-info/METADATA
dingtalk_utils-1.0.4.dist-info/WHEEL
dingtalk_utils-1.0.4.dist-info/top_level.txt
dingtalk_utils-1.0.4.dist-info/RECORD
